Metadata-Version: 2.1
Name: example-pkg-xuhuifan
Version: 0.0.1
Summary: Spatial partition inference
Home-page: https://github.com/pypa/sampleproject
Author: Xuhui Fan
Author-email: xhfan.ml@gmail.com
License: UNKNOWN
Platform: UNKNOWN
Classifier: Programming Language :: Python :: 3
Classifier: License :: OSI Approved :: MIT License
Classifier: Operating System :: OS Independent
Requires-Python: >=3.6
